{
    "account": {
        "assetCount": 514,
        "balance": 146,
        "height": 919,
        "index": 14,
        "inventoryNonce": 518,
        "keys": {
            "master": {
                "key": {
                    "groupName": "secp256k1",
                    "publicKey": "038B85434FA4B9730FB40B24C6044A9FC39F38AEE13DA7658BC53D7C23F322EDD8",
                    "type": "EC_HEX"
                },
                "policy": {
                    "base": "beta-key"
                }
            }
        },
        "name": "sprocket314",
        "nonce": 111,
        "policy": {
            "base": ""
        }
    },
    "entitlements": {
        "account": {
            "policy": {
                "children": {
                    "MAX_ASSETS": {
                        "lower": {
                            "enabled": false,
                            "exclude": false,
                            "limit": 0
                        },
                        "type": "numeric",
                        "upper": {
                            "enabled": false,
                            "exclude": false,
                            "limit": 0
                        }
                    },
                    "MAX_VOL": {
                        "lower": {
                            "enabled": false,
                            "exclude": false,
                            "limit": 0
                        },
                        "type": "numeric",
                        "upper": {
                            "enabled": false,
                            "exclude": false,
                            "limit": 0
                        }
                    }
                },
                "type": "path"
            }
        },
        "keys": {
            "master": {
                "policy": {
                    "children": {
                        "BETA_GET_DECK": {
                            "type": "boolean",
                            "value": true
                        },
                        "RENAME_ACCOUNT": {
                            "type": "boolean",
                            "value": true
                        },
                        "RUN_SCRIPT": {
                            "type": "boolean",
                            "value": true
                        },
                        "SEND_ASSETS": {
                            "type": "boolean",
                            "value": true
                        },
                        "SEND_VOL": {
                            "type": "boolean",
                            "value": true
                        },
                        "UPGRADE_ASSETS": {
                            "type": "boolean",
                            "value": true
                        }
                    },
                    "type": "path"
                }
            }
        }
    }
}